.hgignore
.hgtags
CHANGES.txt
MANIFEST.in
README.txt
i18n.sh
setup.py
src/maahinkainen/__init__.py
src/maahinkainen.portlet.googlecalendar.egg-info/PKG-INFO
src/maahinkainen.portlet.googlecalendar.egg-info/SOURCES.txt
src/maahinkainen.portlet.googlecalendar.egg-info/dependency_links.txt
src/maahinkainen.portlet.googlecalendar.egg-info/entry_points.txt
src/maahinkainen.portlet.googlecalendar.egg-info/namespace_packages.txt
src/maahinkainen.portlet.googlecalendar.egg-info/not-zip-safe
src/maahinkainen.portlet.googlecalendar.egg-info/requires.txt
src/maahinkainen.portlet.googlecalendar.egg-info/top_level.txt
src/maahinkainen/portlet/__init__.py
src/maahinkainen/portlet/googlecalendar/__init__.py
src/maahinkainen/portlet/googlecalendar/agenda.pt
src/maahinkainen/portlet/googlecalendar/browser.py
src/maahinkainen/portlet/googlecalendar/configure.zcml
src/maahinkainen/portlet/googlecalendar/event.pt
src/maahinkainen/portlet/googlecalendar/events.pt
src/maahinkainen/portlet/googlecalendar/googlecalendar.py
src/maahinkainen/portlet/googlecalendar/interfaces.py
src/maahinkainen/portlet/googlecalendar/month.pt
src/maahinkainen/portlet/googlecalendar/portlet.py
src/maahinkainen/portlet/googlecalendar/upgrades.py
src/maahinkainen/portlet/googlecalendar/upgrades.zcml
src/maahinkainen/portlet/googlecalendar/utility.py
src/maahinkainen/portlet/googlecalendar/locales/maahinkainen.portlet.googlecalendar.pot
src/maahinkainen/portlet/googlecalendar/locales/en/LC_MESSAGES/maahinkainen.portlet.googlecalendar.mo
src/maahinkainen/portlet/googlecalendar/locales/en/LC_MESSAGES/maahinkainen.portlet.googlecalendar.po
src/maahinkainen/portlet/googlecalendar/locales/fi/LC_MESSAGES/maahinkainen.portlet.googlecalendar.mo
src/maahinkainen/portlet/googlecalendar/locales/fi/LC_MESSAGES/maahinkainen.portlet.googlecalendar.po
src/maahinkainen/portlet/googlecalendar/profiles/default/cssregistry.xml
src/maahinkainen/portlet/googlecalendar/profiles/default/jsregistry.xml
src/maahinkainen/portlet/googlecalendar/profiles/default/metadata.xml
src/maahinkainen/portlet/googlecalendar/profiles/default/portlets.xml
src/maahinkainen/portlet/googlecalendar/profiles/upgrade1to2/cssregistry.xml
src/maahinkainen/portlet/googlecalendar/profiles/upgrade1to2/metadata.xml
src/maahinkainen/portlet/googlecalendar/static/googlecalendar.css
src/maahinkainen/portlet/googlecalendar/static/overlay.js