Metadata-Version: 1.0
Name: maahinkainen.portlet.googlecalendar
Version: 1.0.1
Summary: Simple Google Calendar events portlet
Home-page: https://github.com/datakurre/maahinkainen.portlet.googlecalendar/
Author: Asko Soukka
Author-email: asko.soukka@iki.fi
License: GPL
Platform: UNKNOWN
Classifier: Programming Language :: Python
